pypackitup/__init__.py
pypackitup/helloworld.py
pypackitup-1.0.1.dist-info/METADATA
pypackitup-1.0.1.dist-info/WHEEL
pypackitup-1.0.1.dist-info/licenses/LICENSE
pypackitup-1.0.1.dist-info/RECORD
