Metadata-Version: 2.3
Name: pypackitup
Version: 1.0.1
Summary: Template repository for developing Python packages.
Project-URL: Homepage, https://github.com/wrencode/pypackitup
Project-URL: Issues, https://github.com/wrencode/pypackitup/issues
Author-email: "Wren J. Rudolph for Wrencode, LLC" <dev@wrencode.com>
License: MIT
Classifier: License :: OSI Approved :: MIT License
Classifier: Operating System :: OS Independent
Classifier: Programming Language :: Python :: 3
Classifier: Programming Language :: Python :: 3.9
Classifier: Programming Language :: Python :: 3.10
Classifier: Programming Language :: Python :: 3.11
Classifier: Programming Language :: Python :: 3.12
Classifier: Programming Language :: Python :: 3.13
Requires-Python: >=3.9
